MANIFEST.in
README.rst
setup.py
warpdrive/__init__.py
warpdrive.egg-info/PKG-INFO
warpdrive.egg-info/SOURCES.txt
warpdrive.egg-info/dependency_links.txt
warpdrive.egg-info/entry_points.txt
warpdrive.egg-info/top_level.txt
warpdrive/bin/warpdrive
warpdrive/etc/__init__.py
warpdrive/etc/base-debian
warpdrive/etc/shell-init
warpdrive/etc/shell-rcfile
warpdrive/etc/start-gunicorn
warpdrive/etc/start-mod_wsgi
warpdrive/etc/start-python
warpdrive/etc/start-shell
warpdrive/etc/start-uwsgi
warpdrive/etc/start-waitress
warpdrive/etc/warpdrive-activate
warpdrive/etc/warpdrive-alive
warpdrive/etc/warpdrive-base
warpdrive/etc/warpdrive-build
warpdrive/etc/warpdrive-destroy
warpdrive/etc/warpdrive-enter
warpdrive/etc/warpdrive-env
warpdrive/etc/warpdrive-exec
warpdrive/etc/warpdrive-fixup
warpdrive/etc/warpdrive-help
warpdrive/etc/warpdrive-image
warpdrive/etc/warpdrive-migrate
warpdrive/etc/warpdrive-profile
warpdrive/etc/warpdrive-rcfile
warpdrive/etc/warpdrive-ready
warpdrive/etc/warpdrive-setup
warpdrive/etc/warpdrive-shell
warpdrive/etc/warpdrive-start
warpdrive/etc/warpdrive-verify
warpdrive/etc/warpdrive-wheels