Metadata-Version: 1.1
Name: warpdrive
Version: 0.32.0
Summary: Launcher for Python web applications.
Home-page: https://github.com/GrahamDumpleton/warpdrive
Author: Graham Dumpleton
Author-email: Graham.Dumpleton@gmail.com
License: BSD
Keywords: wgsi docker openshift
Platform: UNKNOWN
Classifier: Development Status :: 4 - Beta
Classifier: License :: OSI Approved :: BSD License
Classifier: Operating System :: MacOS :: MacOS X
Classifier: Operating System :: POSIX :: Linux
Classifier: Programming Language :: Python :: 3.6
Classifier: Programming Language :: Python :: 3.7
Classifier: Programming Language :: Python :: 3.8
Classifier: Topic :: Internet :: WWW/HTTP :: WSGI
